doi2bib3/APS_replacement.json
doi2bib3/Nature_replacement.json
doi2bib3/__init__.py
doi2bib3/backend.py
doi2bib3/utils.py
doi2bib3-0.5.2.dist-info/licenses/LICENSE
doi2bib3-0.5.2.dist-info/METADATA
doi2bib3-0.5.2.dist-info/WHEEL
doi2bib3-0.5.2.dist-info/entry_points.txt
doi2bib3-0.5.2.dist-info/top_level.txt
doi2bib3-0.5.2.dist-info/RECORD
