Metadata-Version: 2.4
Name: doi2bib3
Version: 0.5.2
Summary: Fetch BibTeX from DOI, arXiv ID, journal URL and article title
Author-email: Archisman Panigrahi <apandada1@gmail.com>
Maintainer-email: Archisman Panigrahi <apandada1@gmail.com>
License-Expression: GPL-3.0-only
Project-URL: Homepage, https://github.com/archisman-panigrahi/doi2bib3
Project-URL: Source, https://github.com/archisman-panigrahi/doi2bib3
Project-URL: Bug Tracker, https://github.com/archisman-panigrahi/doi2bib3/issues
Keywords: doi,bibtex,arxiv
Classifier: Operating System :: OS Independent
Requires-Python: >=3.9
License-File: LICENSE
Requires-Dist: requests
Requires-Dist: bibtexparser
Provides-Extra: dev
Requires-Dist: build>=1.2.2.post1; extra == "dev"
Requires-Dist: pytest>=9.0.1; extra == "dev"
Requires-Dist: tox>=4.32.0; extra == "dev"
Dynamic: license-file
